{
  "total_profiles": 3,
  "profiles": [
    {
      "profile_id": "4",
      "description": "## Profile Name and Tagline and Propensity Score | ID: 4\n- **Name**: Urban Green Advocates (UGA)\n- **Tagline**: Young professionals with a strong environmental conscience living in urban areas.\n- **Propensity Score**: GrandCentr = 0.4230769230769231 -> This suggests that they are more likely to be city dwellers who prioritize sustainability, differentiating them from other profiles with lower scores in this area (difference: higher urban-centric score).\n\n### Who Are They? (Storytelling)\nUrban Green Advocates represent a segment of young professionals within the electric scooter market who are deeply engaged and environmentally conscious. With an average age that is lower than other profiles, they have shown to be more receptive to green initiatives, as evidenced by their highest sensitivity towards environmental topics (GreenSurveyScore = 8.327705800115384). Their lifetime value and engagement with the brand are significant indicators of potential loyalty and advocacy for sustainable transport options in urban settings, where they spend time due to their proximity to city centers (LTV = 2.346153846 times higher than average LTV across all profiles).\n\nThe main differentiating factors between Profile ID: 4 customers and other segments are the combination of high GreenSurveyScores, indicating a strong environmental consciousness that aligns with urban living (GrandCentr = highest among all), suggesting they prioritize eco-friendly transportation choices. Their age demographic is also distinctive; being younger on average compared to other profiles suggests they are more adaptable and open to new technologies like electric scooters, which can be a key psychological lever for marketing strategies targeted at urban professionals seeking sustainable mobility solutions in city environments.\n\n### Key Data Insights\n- **GreenSurveyScore** = 8.327705800115384 -> This means they are highly likely to be influenced by green initiatives, differentiating them from other profiles with lower scores (difference: significantly higher GreenSurveyScore).\n- **GrandCentr** = Higher than all other profiles, indicating a customer who lives in urban context and prioritizes sustainability -> This suggests they are more likely to be city dwellers seeking eco-friendly transportation options.\n- **Age demographic is younger on average compared to other profiles**: Difference - Younger age group may indicate adaptability and openness towards new technologies like electric scooters, which can align with sustainable urban living (difference in Age).\n\n### Actionable Recommendations\n- **Increase** targeted social media campaigns on platforms popular among younger professionals. Use visual content that highlights the environmental benefits of using electric scooters and features real stories from within this demographic to showcase lifestyle integration with sustainability goals (justified by GreenSurveyScore = highest across all profiles).\n- **Partner** with local urban businesses for co-promotions or pop-up events that offer discounts on electric scooters, leveraging the high engagement and loyalty of this group to drive word-of-mouth marketing (justified by LTV = significantly higher across all profiles).\n\n### Watch Out For\n- **Risks**: Younger demographics may have less disposable income or financial stability compared to older segments, potentially affecting their purchasing power. This could be a risk if not addressed with"
    },
    {
      "profile_id": "7",
      "description": "## Profile Name and Tagline and Propensity Score | ID: 7\n- **Name**: The Eco-Conscious Professional Explorer\n- **Tagline**: Highly engaged professionals with strong environmental values, spending above average on eco-friendly transport.\n- **Propensity Score**: HP = 0.3125 (from profile_stats) -> Indicates a moderate propensity to purchase among this group of customers who are employed and have shown interest in sustainability, with the highest GreenSurveyScore influencing their purchasing decisions significantly.\n\n### Who Are They? (Storytelling)\nThis customer segment consists predominantly of Employees (Professione_Impiegato), representing a significant portion of our clientele who have made 2 electric scooter acquisitions in the past year and spend on average $467 monthly, which is above median spending levels. They are highly engaged with digital platforms at an engagement level of 0.75 (from profile_stats), suggesting a strong alignment with our brand's sustainability messaging through CRM channels and app usage. The most notable aspect differentiating this group from others, based on the odds ratios provided in SHAP analysis, is their high lifetime value score of 2.6875 (from profile_stats), indicating they are not only engaged but also have a substantial financial commitment to our brand and products over time.\n\n### Key Data Insights\n- **Capacita_d_ spsa** = 2.84375 -> Indicates these customers, on average, spend more than the median customer in terms of purchasing power towards eco-friendly transport options and are likely to continue doing so given their high GreenSurveyScore impact (from SHAP)\n- **LTV** = 2.6875 -> Suggests that these customers contribute significantly to our revenue over time, making them valuable assets for retention strategies\n- **RFM_Score** = 6.9375 -> Reflects their loyalty and frequent purchasing behavior within the last year (from profile_stats), which is a strong indicator of potential future sales if targeted correctly\n- **Engagement** = 0.74918 (from profile_stats) -> High engagement levels suggest they are receptive to personalized marketing efforts, especially those aligned with environmental sustainability\n\n### Actionable Recommendations\nLaunch a digital campaign highlighting the eco-friendly aspects of our electric scooters and target this group through email and in-app messaging. Reference their high engagement levels (0.74918) to increase personalized content relevance, focusing on how purchasing these products can further reduce carbon footprints based on the GreenSurveyScore impact of 7.8571 (from profile_stats).\n\n### Watch Out For\nThe primary risk for this segment is their relatively lower propensity to purchase compared to others with higher scores, as indicated by a cluster_propensity score of only 0.3279 and leaf_id impacts suggesting they are not the highest spenders in our customer base (from SHAP analysis). This group might require additional nudges or loyalty rewards to convert their engagement into sales more effectively.\n\n---"
    },
    {
      "profile_id": "Generic",
      "description": "## Profile Name and Tagline and Propensity Score | ID: Generic\n- **Name**: The Eco-Conscious Pensioner Segment (Note that due to the constraints, we're avoiding using \"Generic\" directly in our name but are still addressing this low propensity profile)\n- **Tagline**: Highly engaged and environmentally conscious pensioners with a strong interest in electric mobility.\n- **Propensity Score**: HP = 0.0615835777126099, suggesting these customers have some likelihood of purchase but are not the primary target for new offerings due to their lower profile volume and propensity score compared to other segments.\n\n### Who Are They? (Storytelling)\nThe Eco-Conscious Pensioner Segment consists of individuals who, on average, have been with us for 5.392961876832844 years and spend $1.89 per month in the last year on electric scooter products (Numero di Prodtti Aquistati negli ultimi 12 mesi = 1.436950146627566), indicating a consistent but not overwhelming interest and engagement with our brand's sustainability messaging, as reflected in their GreenSurveyScore of 7.211801604733138 out of 10. Despite being retired or nearing retirement age (Life Cycle = ALTRO), these customers have shown a notable level of engagement with digital marketing efforts, as evidenced by an Engagement score of 0.5846717695131964 and LivelloDigitalizzazione of 2.404692082111437 out of a possible maximum. This segment is particularly unique because, despite their age group's traditional lower digital engagement levels (GrandCentr = 0.2785923753665689), they have demonstrated an above-average lifetime value and loyalty to the brand, as indicated by a high RFM Score of 3.7653958944281527 (LTV = 1.6979472140762464).\n\n### Key Data Insights\n- **Capacita_d_ spsa** = 1.8914956011730208 -> These customers have substantial purchasing power, suggesting they can afford and are interested in high-end electric scooters, which could justify premium pricing strategies or loyalty programs tailored to their financial capacity (LTV = 1.6979472140762464).\n- **RFM_Score** = 3.7653958944281527 -> This score reflects a strong customer base with high recency and frequency of purchases, indicating they are likely repeat buyers who value the brand's offerings highly compared to other segments that might have lower scores or engagement levels.\n- **GreenSurveyScore** = 7.211801604733138 -> This high score among pensioned customers suggests a strong alignment with environmental values, which can be leveraged in targeted marketing campaigns emphasizing the eco-friendly aspects of electric scooters to resonate deeply with this group's sensitivity towards green"
    }
  ]
}